vertagus/__init__.py
vertagus/factory.py
vertagus/operations.py
vertagus/aliases/__init__.py
vertagus/aliases/library.py
vertagus/aliases/loader.py
vertagus/bumpers/__init__.py
vertagus/bumpers/registry.py
vertagus/bumpers/semantic.py
vertagus/cli/__init__.py
vertagus/cli/cli.py
vertagus/cli/formatting.py
vertagus/cli/utils.py
vertagus/cli/commands/__init__.py
vertagus/cli/commands/bump.py
vertagus/cli/commands/create_aliases.py
vertagus/cli/commands/create_tag.py
vertagus/cli/commands/init.py
vertagus/cli/commands/list_aliases.py
vertagus/cli/commands/list_bumpers.py
vertagus/cli/commands/list_manifests.py
vertagus/cli/commands/list_rules.py
vertagus/cli/commands/list_scms.py
vertagus/cli/commands/show_alias.py
vertagus/cli/commands/show_version.py
vertagus/cli/commands/validate.py
vertagus/configuration/__init__.py
vertagus/configuration/load.py
vertagus/configuration/types.py
vertagus/core/__init__.py
vertagus/core/bumper_base.py
vertagus/core/manifest_base.py
vertagus/core/package_base.py
vertagus/core/project.py
vertagus/core/rule_bases.py
vertagus/core/scm_base.py
vertagus/core/stage.py
vertagus/core/tag_base.py
vertagus/providers/__init__.py
vertagus/providers/manifest/__init__.py
vertagus/providers/manifest/json_manifest.py
vertagus/providers/manifest/registry.py
vertagus/providers/manifest/toml_manifest.py
vertagus/providers/manifest/yaml_manifest.py
vertagus/providers/manifest/setuptools_/__init__.py
vertagus/providers/manifest/setuptools_/pyproject_manifest.py
vertagus/providers/scm/__init__.py
vertagus/providers/scm/registry.py
vertagus/providers/scm/git_/__init__.py
vertagus/providers/scm/git_/git_scm.py
vertagus/rules/__init__.py
vertagus/rules/comparison/__init__.py
vertagus/rules/comparison/library.py
vertagus/rules/comparison/loader.py
vertagus/rules/single_version/__init__.py
vertagus/rules/single_version/library.py
vertagus/rules/single_version/loader.py
vertagus/utils/__init__.py
vertagus/utils/config.py
vertagus/utils/factory.py
vertagus-0.4.1.dist-info/licenses/LICENSE
vertagus-0.4.1.dist-info/METADATA
vertagus-0.4.1.dist-info/WHEEL
vertagus-0.4.1.dist-info/entry_points.txt
vertagus-0.4.1.dist-info/top_level.txt
vertagus-0.4.1.dist-info/RECORD
