Metadata-Version: 2.4
Name: vertagus
Version: 0.4.1
Summary: A tool to assist the maintenance of package versioning via manifests and source control.
Author-email: John Raines <johndanielraines@gmail.com>
License: Copyright (c) 2024 John Raines
Project-URL: Homepage, https://github.com/jdraines/vertagus
Project-URL: Documentation, https://jdraines.github.io/vertagus/
Project-URL: Repository, https://github.com/jdraines/vertagus
Project-URL: Bug Tracker, https://github.com/jdraines/vertagus/issues
Classifier: Development Status :: 5 - Production/Stable
Classifier: Intended Audience :: Developers
Classifier: Topic :: Software Development
Classifier: License :: OSI Approved :: MIT License
Classifier: Programming Language :: Python :: 3
Classifier: Programming Language :: Python :: 3.9
Classifier: Programming Language :: Python :: 3.10
Classifier: Programming Language :: Python :: 3.11
Classifier: Programming Language :: Python :: 3.12
Classifier: Programming Language :: Python :: 3.13
License-File: LICENSE
Requires-Dist: click<9,>=8.1.7
Requires-Dist: GitPython==3.1.43
Requires-Dist: tomli<3,>=2.0.2
Requires-Dist: tomli-w<2,>=1.2.0
Requires-Dist: packaging==24.1
Requires-Dist: PyYAML>=6
Provides-Extra: dev
Requires-Dist: pytest; extra == "dev"
Requires-Dist: pytest-cov; extra == "dev"
Requires-Dist: ruff; extra == "dev"
Provides-Extra: docs
Requires-Dist: mkdocs>=1.5.0; extra == "docs"
Requires-Dist: mkdocs-material>=9.0.0; extra == "docs"
Requires-Dist: mkdocstrings[python]>=0.20.0; extra == "docs"
Requires-Dist: mkdocs-gen-files>=0.4.0; extra == "docs"
Requires-Dist: mkdocs-literate-nav>=0.6.0; extra == "docs"
Requires-Dist: mkdocs-section-index>=0.3.0; extra == "docs"
Requires-Dist: mike>=2.0.0; extra == "docs"
Dynamic: license-file
